llama_index/voice_agents/elevenlabs/__init__.py
llama_index/voice_agents/elevenlabs/base.py
llama_index/voice_agents/elevenlabs/events.py
llama_index/voice_agents/elevenlabs/interface.py
llama_index/voice_agents/elevenlabs/utils.py
llama_index_voice_agents_elevenlabs-0.4.1.dist-info/METADATA
llama_index_voice_agents_elevenlabs-0.4.1.dist-info/WHEEL
llama_index_voice_agents_elevenlabs-0.4.1.dist-info/licenses/LICENSE
llama_index_voice_agents_elevenlabs-0.4.1.dist-info/RECORD
