Metadata-Version: 2.4
Name: llama-index-voice-agents-elevenlabs
Version: 0.4.1
Summary: LlamaIndex x ElevenLabs integration
Author-email: Clelia Astra Bertelli <clelia@runllama.ai>
Maintainer: AstraBert
License-Expression: MIT
License-File: LICENSE
Requires-Python: <4.0,>=3.9
Requires-Dist: elevenlabs[pyaudio]<3,>=2.1.0
Requires-Dist: llama-index-core<0.15,>=0.13.0
Requires-Dist: websockets<16,>=15
